af_sdk/__init__.py
af_sdk/auth/__init__.py
af_sdk/auth/dpop.py
af_sdk/auth/oauth.py
af_sdk/auth/token_cache.py
af_sdk/connectors/__init__.py
af_sdk/connectors/base.py
af_sdk/connectors/registry.py
af_sdk/dx/__init__.py
af_sdk/dx/decorators.py
af_sdk/dx/runtime.py
af_sdk/events.py
af_sdk/exceptions.py
af_sdk/fabriq_client.py
af_sdk/models/__init__.py
af_sdk/models/audit.py
af_sdk/models/types.py
af_sdk/py.typed
af_sdk/transport/__init__.py
af_sdk/transport/http.py
af_sdk/vault.py
agentic_fabric_sdk-0.1.3.dist-info/METADATA
agentic_fabric_sdk-0.1.3.dist-info/WHEEL
agentic_fabric_sdk-0.1.3.dist-info/RECORD
