Metadata-Version: 2.4
Name: agentic-fabric-sdk
Version: 0.1.3
Summary: Fabriq/Agentic Fabric Python SDK: high-level client, DX helpers, auth
License: Apache-2.0
Keywords: fabriq,agentic-fabric,sdk,ai,agents
Author: Agentic Fabric Contributors
Author-email: contributors@agentic-fabric.org
Requires-Python: >=3.11,<3.13
Classifier: Development Status :: 4 - Beta
Classifier: Intended Audience :: Developers
Classifier: License :: OSI Approved :: Apache Software License
Classifier: Programming Language :: Python :: 3
Classifier: Programming Language :: Python :: 3.11
Classifier: Programming Language :: Python :: 3.12
Classifier: Typing :: Typed
Requires-Dist: PyJWT (>=2.8.0)
Requires-Dist: httpx (>=0.25)
Requires-Dist: pydantic (>=2.4)
Requires-Dist: stevedore (>=5.1.0)
Requires-Dist: typing-extensions
Project-URL: Documentation, https://docs.agentic-fabric.org
Project-URL: Homepage, https://github.com/agentic-fabric/agentic-fabric
Project-URL: Repository, https://github.com/agentic-fabric/agentic-fabric
